[
  {
    "id": 1,
    "name": "Đồng Hành Sinh Hoạt Hằng Ngày",
    "image": "assets/bai-viet-ve-sinh-ca-nhan-cho-nguoi-gia-dung-cach.png",
    "alt": "Dich vu dong hanh sinh hoat hang ngay cho nguoi cao tuoi tai nha",
    "description": "Phù hợp cho người cao tuổi còn tự chủ một phần, cần thêm người hỗ trợ để sinh hoạt đều đặn, an toàn và đỡ vất vả khi không có con cháu bên cạnh.",
    "includes": [
      "Chuẩn bị bữa ăn hằng ngày, nhắc giờ ăn uống và dọn dẹp sau bữa",
      "Hỗ trợ đi chợ, mua thuốc theo toa có sẵn và các vật dụng thiết yếu trong nhà",
      "Nhắc lịch sinh hoạt, đồng hành đi bộ nhẹ hoặc tập vận động cơ bản theo thói quen",
      "Hỗ trợ tắm rửa, gội đầu, thay đồ khi người già mệt hoặc khó tự làm",
      "Giặt giũ, sắp xếp quần áo, dọn phòng ngủ và khu vực sinh hoạt gọn gàng",
      "Trò chuyện, đọc báo, nghe nhạc để người già bớt buồn chán và cô đơn"
    ],
    "pricing": [
      {
        "label": "Cả ngày 24h",
        "value": 1400000,
        "hours": 24,
        "type": "day_full"
      },
      {
        "label": "khác",
        "value": 50000,
        "hours": 1,
        "type": "gio"
      }
    ]
  },
  {
    "id": 2,
    "name": "Hỗ Trợ Người Già Khó Đi Lại",
    "image": "assets/bai-viet-tam-ly-nguoi-cao-tuoi-khong-the-tu-cham-soc.png",
    "alt": "Dich vu ho tro nguoi gia kho di lai an toan tai nha",
    "description": "Dành cho người cao tuổi đi lại chậm, đau khớp hoặc dễ mất thăng bằng, cần người kề bên để hỗ trợ an toàn trong các việc cá nhân hằng ngày.",
    "includes": [
      "Dìu đỡ khi đứng lên ngồi xuống, đi lại trong nhà và lên xuống cầu thang",
      "Hỗ trợ đi vệ sinh, vệ sinh cá nhân sau khi đi vệ sinh và thay quần áo sạch",
      "Nấu ăn mềm, dễ nhai nuốt; hỗ trợ bày bữa và theo dõi người già ăn uống đầy đủ",
      "Sắp xếp nhà cửa thông thoáng, hạn chế vật cản để giảm nguy cơ té ngã",
      "Chuẩn bị đồ dùng hằng ngày trong tầm với để người già tiện sử dụng",
      "Đồng hành đi khám theo lịch, hỗ trợ di chuyển và chờ khám cùng người già"
    ],
    "pricing": [
      {
        "label": "Cả ngày 24h",
        "value": 1400000,
        "hours": 24,
        "type": "day_full"
      },
      {
        "label": "khác",
        "value": 50000,
        "hours": 1,
        "type": "gio"
      }
    ]
  },

  {
    "id": 3,
    "name": "Hỗ Trợ Người Già Suy Yếu Nhiều",
    "image": "assets/bai-viet-nguyen-tac-dinh-duong-cho-nguoi-gia-nam-liet.png",
    "alt": "Dich vu ho tro nguoi gia suy yeu nhieu can cham soc thuong xuyen",
    "description": "Phù hợp cho người cao tuổi suy yếu, ăn ngủ thất thường hoặc cần hỗ trợ gần như cả ngày để duy trì nếp sinh hoạt ổn định và sạch sẽ.",
    "includes": [
      "Hỗ trợ ăn uống tại giường hoặc tại ghế, chuẩn bị phần ăn nhỏ dễ dùng",
      "Hỗ trợ tắm lau, gội đầu, thay đồ và vệ sinh thân thể mỗi ngày",
      "Hỗ trợ thay tã, xử lý đồ bẩn, giữ cơ thể và chỗ nằm luôn khô thoáng",
      "Xoay trở, đổi tư thế nằm ngồi thường xuyên để người già đỡ mỏi",
      "Thay ga gối, giặt giũ đồ cá nhân và dọn sạch khu vực nghỉ ngơi",
      "Ghi nhận tình hình ăn ngủ, tinh thần trong ngày và cập nhật cho gia đình"
    ],
    "pricing": [
      {
        "label": "Cả ngày 24h",
        "value": 1400000,
        "hours": 24,
        "type": "day_full"
      },
      {
        "label": "khác",
        "value": 50000,
        "hours": 1,
        "type": "gio"
      }
    ]
  },

  {
    "id": 4,
    "name": "Hỗ Trợ Chăm Sóc 24/7 Cho Người Già Phụ Thuộc Hoàn Toàn",
    "image": "assets/bai-viet-cach-phong-ngua-loet-ti-de-o-nguoi-gia.png",
    "alt": "Dich vu cham soc nguoi gia phu thuoc hoan toan 24 7",
    "description": "Giải pháp cho người cao tuổi cần người túc trực liên tục ngày đêm vì không thể tự sinh hoạt, giúp gia đình yên tâm khi không thể chăm trực tiếp.",
    "includes": [
      "Túc trực theo ca 24/7, hỗ trợ toàn bộ ăn uống, vệ sinh và thay đồ đúng thời điểm",
      "Theo sát nhu cầu ban ngày và ban đêm, báo ngay cho gia đình khi có bất thường trong sinh hoạt",
      "Hỗ trợ di chuyển bằng xe lăn hoặc dụng cụ sẵn có khi cần đổi không gian",
      "Chuẩn bị và quản lý đồ dùng thiết yếu: tã, khăn, quần áo, vật dụng vệ sinh",
      "Dọn dẹp phòng ở sạch sẽ, sắp xếp đồ đạc an toàn cho việc chăm sóc lâu dài",
      "Đồng hành trò chuyện, tạo cảm giác được quan tâm để người già an tâm và dễ ngủ hơn"
    ],
    "pricing": [
      {
        "label": "Cả ngày 24h",
        "value": 1400000,
        "hours": 24,
        "type": "day_full"
      },
      {
        "label": "khác",
        "value": 50000,
        "hours": 1,
        "type": "gio"
      }
    ]
  }

]